smoothfdr/__init__.py
smoothfdr/gen2d.py
smoothfdr/neuropost.py
smoothfdr/neuropre.py
smoothfdr/normix.py
smoothfdr/plotutils.py
smoothfdr/sfdr.py
smoothfdr/signal_distributions.py
smoothfdr/smoothed_fdr.py
smoothfdr/utils.py
smoothfdr-0.9.4.dist-info/DESCRIPTION.rst
smoothfdr-0.9.4.dist-info/entry_points.txt
smoothfdr-0.9.4.dist-info/METADATA
smoothfdr-0.9.4.dist-info/metadata.json
smoothfdr-0.9.4.dist-info/RECORD
smoothfdr-0.9.4.dist-info/top_level.txt
smoothfdr-0.9.4.dist-info/WHEEL
