Metadata-Version: 2.0
Name: smoothfdr
Version: 0.9.4
Summary: False discovery rate smoothing
Home-page: https://github.com/tansey/smoothfdr
Author: Wesley Tansey
Author-email: tansey@cs.utexas.edu
License: MIT
Keywords: statistics biostatistics fdr hypothesis machinelearning
Platform: UNKNOWN
Classifier: Development Status :: 3 - Alpha
Classifier: Intended Audience :: Science/Research
Classifier: Topic :: Scientific/Engineering
Classifier: License :: OSI Approved :: MIT License
Classifier: Programming Language :: Python :: 2
Classifier: Programming Language :: Python :: 2.7
Requires-Dist: numpy
Requires-Dist: scipy
Requires-Dist: matplotlib
Requires-Dist: pygfl
